ntdsdotsqlite/__init__.py
ntdsdotsqlite/__main__.py
ntdsdotsqlite/basehandler.py
ntdsdotsqlite/computerhandler.py
ntdsdotsqlite/containerhandler.py
ntdsdotsqlite/decrypt.py
ntdsdotsqlite/domainhandler.py
ntdsdotsqlite/grouphandler.py
ntdsdotsqlite/model.sql
ntdsdotsqlite/ntdsdotsqlite.py
ntdsdotsqlite/organizationalunithandler.py
ntdsdotsqlite/personhandler.py
ntdsdotsqlite/trusteddomainhandler.py
ntdsdotsqlite/utils.py
ntdsdotsqlite-1.1.7.dist-info/entry_points.txt
ntdsdotsqlite-1.1.7.dist-info/WHEEL
ntdsdotsqlite-1.1.7.dist-info/METADATA
ntdsdotsqlite-1.1.7.dist-info/RECORD
