Metadata-Version: 2.1
Name: ntdsdotsqlite
Version: 1.1.7
Summary: A small utility to get an SQLite  database from an NTDS.DIT file.
Home-page: https://github.com/almandin/ntdsdotsqlite
License: Beerware
Author: Virgile Jarry
Author-email: virgile@mailbox.org
Requires-Python: >=3.9,<4.0
Classifier: License :: Other/Proprietary License
Classifier: Programming Language :: Python :: 3
Classifier: Programming Language :: Python :: 3.9
Classifier: Programming Language :: Python :: 3.10
Classifier: Programming Language :: Python :: 3.11
Requires-Dist: dissect[ese] (>=3.5,<4.0)
Requires-Dist: impacket (>=0.10,<0.11)
Requires-Dist: pycryptodomex (>=3.18.0,<4.0.0)
Requires-Dist: tqdm (>=4.65.0,<5.0.0)
Project-URL: Documentation, https://github.com/almandin/ntdsdotsqlite/README.md
Project-URL: Repository, https://github.com/almandin/ntdsdotsqlite
